shopify_python/__init__.py
shopify_python/ast.py
shopify_python/git_utils.py
shopify_python/google_styleguide.py
shopify_python/packaging.py
shopify_python/py.typed
shopify_python/shopify_styleguide.py
shopify_python-0.6.3.dist-info/LICENSE
shopify_python-0.6.3.dist-info/METADATA
shopify_python-0.6.3.dist-info/WHEEL
shopify_python-0.6.3.dist-info/top_level.txt
shopify_python-0.6.3.dist-info/RECORD
