Metadata-Version: 2.1
Name: shopify-python
Version: 0.6.3
Summary: Python Standards Library for Shopify
Home-page: http://github.com/shopify/shopify_python
Author: Shopify Data Acceleration
Author-email: data-acceleration@shopify.com
License: MIT
Classifier: Development Status :: 2 - Pre-Alpha
Classifier: Intended Audience :: Developers
Classifier: License :: OSI Approved :: MIT License
Classifier: Natural Language :: English
Classifier: Programming Language :: Python :: 3
Classifier: Programming Language :: Python :: 2
License-File: LICENSE
Requires-Dist: autopep8 (~=1.4)
Requires-Dist: GitPython (~=2.1.11) ; python_version < "3.0"
Requires-Dist: typing (~=3.6.6) ; python_version < "3.5"
Requires-Dist: GitPython (>=3.1.30) ; python_version >= "3.0"
Requires-Dist: pylint (~=1.9.3) ; python_version<"3.0"
Requires-Dist: pylint (>=2.1.1) ; python_version>="3.0"
